Metadata-Version: 2.1
Name: cpgame
Version: 0.5
Summary: Simple game framework for CircuitPython embedded hardware
Home-page: https://github.com/jreese/cpgame
Author: John Reese
Author-email: john@noswap.com
License: MIT
Platform: UNKNOWN
Classifier: Development Status :: 4 - Beta
Classifier: Intended Audience :: Developers
Classifier: License :: OSI Approved :: MIT License
Classifier: Programming Language :: Python
Classifier: Programming Language :: Python :: 3
Classifier: Programming Language :: Python :: 3.5
Classifier: Topic :: Software Development :: Libraries
Requires-Python: >=3.6
